sctreeshap.py
sctreeshap-0.7.6.1.dist-info/LICENSE
sctreeshap-0.7.6.1.dist-info/METADATA
sctreeshap-0.7.6.1.dist-info/WHEEL
sctreeshap-0.7.6.1.dist-info/top_level.txt
sctreeshap-0.7.6.1.dist-info/RECORD
