Metadata-Version: 2.1
Name: sctreeshap
Version: 0.7.6.1
Summary: sctreeshap: a cluster tree data structure, and for shap analysis
Home-page: https://github.com/ForwardStar/sctreeshap
Author: Haoxuan Xie
Author-email: haoxuanxie@link.cuhk.edu.cn
License: LICENSE
Platform: UNKNOWN
Classifier: Programming Language :: Python :: 3.8
Classifier: License :: OSI Approved :: MIT License
Classifier: Operating System :: OS Independent
Requires-Python: >=3.8
License-File: LICENSE
Requires-Dist: shap (>=0.39.0)
Requires-Dist: matplotlib (>=3.4.2)
Requires-Dist: anndata (>=0.7.6)
Requires-Dist: numpy (>=1.19.5)
Requires-Dist: pandas (>=1.2.4)
Requires-Dist: sklearn (>=0.0)
Requires-Dist: scikit-learn (>=0.24.2)
Requires-Dist: imblearn (>=0.0)
Requires-Dist: imbalanced-learn (>=0.8.0)
Requires-Dist: xgboost (>=1.4.2)
Requires-Dist: loompy (>=3.0.6)
Requires-Dist: tqdm (>=4.61.2)
Requires-Dist: requests (>=2.26.0)
Requires-Dist: pathlib2 (>=2.0)
Requires-Dist: pip (>=21.1.3)
